wu_toolkit/__init__.py
wu_toolkit/__version__.py
wu_toolkit/app_config.py
wu_toolkit/command.py
wu_toolkit/script/__init__.py
wu_toolkit/script/neb_aseview_.py
wu_toolkit/script/vesta_op.py
wu_toolkit-1.4.2.dist-info/LICENSE
wu_toolkit-1.4.2.dist-info/METADATA
wu_toolkit-1.4.2.dist-info/WHEEL
wu_toolkit-1.4.2.dist-info/entry_points.txt
wu_toolkit-1.4.2.dist-info/RECORD
