Metadata-Version: 2.1
Name: wu_toolkit
Version: 1.4.2
Summary: 个人用的命令包
License: GPLv3
Keywords: python,toolkit,modeling
Author: wuyaos
Author-email: wufeifeng_hust@163.com
Requires-Python: >=3.7
Classifier: Development Status :: 3 - Alpha
Classifier: Environment :: Console
Classifier: License :: Other/Proprietary License
Classifier: Operating System :: OS Independent
Classifier: Programming Language :: Python :: 3
Classifier: Programming Language :: Python :: 3.7
Classifier: Programming Language :: Python :: 3.8
Classifier: Programming Language :: Python :: 3.9
Classifier: Programming Language :: Python :: 3.10
Classifier: Programming Language :: Python :: 3.11
Classifier: Programming Language :: Python :: 3.12
Requires-Dist: ase (>=3.21.0)
Requires-Dist: platformdirs (>=4.0.0)
Requires-Dist: typer (>=0.12.1)
